[
  {
    "stck_bsop_date": "20260716",
    "stck_cntg_hour": "090000",
    "stck_prpr": "2740",
    "stck_oprc": "2720",
    "stck_hgpr": "2765",
    "stck_lwpr": "2660",
    "cntg_vol": "514969",
    "acml_tr_pbmn": "1410765046"
  },
  {
    "stck_bsop_date": "20260716",
    "stck_cntg_hour": "090100",
    "stck_prpr": "2680",
    "stck_oprc": "2750",
    "stck_hgpr": "2850",
    "stck_lwpr": "2680",
    "cntg_vol": "214832",
    "acml_tr_pbmn": "2010230307"
  },
  {
    "stck_bsop_date": "20260716",
    "stck_cntg_hour": "090200",
    "stck_prpr": "2680",
    "stck_oprc": "2680",
    "stck_hgpr": "2680",
    "stck_lwpr": "2680",
    "cntg_vol": "0",
    "acml_tr_pbmn": "2010230307"
  },
  {
    "stck_bsop_date": "20260716",
    "stck_cntg_hour": "090300",
    "stck_prpr": "2740",
    "stck_oprc": "2680",
    "stck_hgpr": "2800",
    "stck_lwpr": "2680",
    "cntg_vol": "277188",
    "acml_tr_pbmn": "2759957417"
  },
  {
    "stck_bsop_date": "20260716",
    "stck_cntg_hour": "090400",
    "stck_prpr": "2680",
    "stck_oprc": "2735",
    "stck_hgpr": "2775",
    "stck_lwpr": "2665",
    "cntg_vol": "225686",
    "acml_tr_pbmn": "3372350847"
  },
  {
    "stck_bsop_date": "20260716",
    "stck_cntg_hour": "090500",
    "stck_prpr": "2775",
    "stck_oprc": "2680",
    "stck_hgpr": "2775",
    "stck_lwpr": "2680",
    "cntg_vol": "209216",
    "acml_tr_pbmn": "3944329227"
  },
  {
    "stck_bsop_date": "20260716",
    "stck_cntg_hour": "090600",
    "stck_prpr": "2920",
    "stck_oprc": "2770",
    "stck_hgpr": "2925",
    "stck_lwpr": "2770",
    "cntg_vol": "391542",
    "acml_tr_pbmn": "5055752361"
  },
  {
    "stck_bsop_date": "20260716",
    "stck_cntg_hour": "090700",
    "stck_prpr": "2945",
    "stck_oprc": "2910",
    "stck_hgpr": "2945",
    "stck_lwpr": "2880",
    "cntg_vol": "210918",
    "acml_tr_pbmn": "5670068779"
  },
  {
    "stck_bsop_date": "20260716",
    "stck_cntg_hour": "090800",
    "stck_prpr": "2945",
    "stck_oprc": "2945",
    "stck_hgpr": "2945",
    "stck_lwpr": "2945",
    "cntg_vol": "0",
    "acml_tr_pbmn": "5670068779"
  },
  {
    "stck_bsop_date": "20260716",
    "stck_cntg_hour": "090900",
    "stck_prpr": "2995",
    "stck_oprc": "2995",
    "stck_hgpr": "3010",
    "stck_lwpr": "2945",
    "cntg_vol": "745398",
    "acml_tr_pbmn": "7894751203"
  },
  {
    "stck_bsop_date": "20260716",
    "stck_cntg_hour": "091000",
    "stck_prpr": "2930",
    "stck_oprc": "2995",
    "stck_hgpr": "3000",
    "stck_lwpr": "2900",
    "cntg_vol": "1006572",
    "acml_tr_pbmn": "10866199469"
  },
  {
    "stck_bsop_date": "20260716",
    "stck_cntg_hour": "091100",
    "stck_prpr": "2875",
    "stck_oprc": "2930",
    "stck_hgpr": "2935",
    "stck_lwpr": "2835",
    "cntg_vol": "685965",
    "acml_tr_pbmn": "12844648055"
  },
  {
    "stck_bsop_date": "20260716",
    "stck_cntg_hour": "091200",
    "stck_prpr": "2845",
    "stck_oprc": "2875",
    "stck_hgpr": "2890",
    "stck_lwpr": "2830",
    "cntg_vol": "332475",
    "acml_tr_pbmn": "13795033894"
  },
  {
    "stck_bsop_date": "20260716",
    "stck_cntg_hour": "091300",
    "stck_prpr": "2845",
    "stck_oprc": "2850",
    "stck_hgpr": "2875",
    "stck_lwpr": "2835",
    "cntg_vol": "236060",
    "acml_tr_pbmn": "14468639564"
  },
  {
    "stck_bsop_date": "20260716",
    "stck_cntg_hour": "091400",
    "stck_prpr": "2780",
    "stck_oprc": "2845",
    "stck_hgpr": "2845",
    "stck_lwpr": "2770",
    "cntg_vol": "397256",
    "acml_tr_pbmn": "15581019240"
  },
  {
    "stck_bsop_date": "20260716",
    "stck_cntg_hour": "091500",
    "stck_prpr": "2750",
    "stck_oprc": "2790",
    "stck_hgpr": "2790",
    "stck_lwpr": "2720",
    "cntg_vol": "333296",
    "acml_tr_pbmn": "16498991425"
  },
  {
    "stck_bsop_date": "20260716",
    "stck_cntg_hour": "091600",
    "stck_prpr": "2715",
    "stck_oprc": "2755",
    "stck_hgpr": "2770",
    "stck_lwpr": "2710",
    "cntg_vol": "167583",
    "acml_tr_pbmn": "16957824572"
  },
  {
    "stck_bsop_date": "20260716",
    "stck_cntg_hour": "091700",
    "stck_prpr": "2735",
    "stck_oprc": "2715",
    "stck_hgpr": "2735",
    "stck_lwpr": "2710",
    "cntg_vol": "98014",
    "acml_tr_pbmn": "17224713349"
  },
  {
    "stck_bsop_date": "20260716",
    "stck_cntg_hour": "091800",
    "stck_prpr": "2735",
    "stck_oprc": "2735",
    "stck_hgpr": "2755",
    "stck_lwpr": "2725",
    "cntg_vol": "100703",
    "acml_tr_pbmn": "17500353371"
  },
  {
    "stck_bsop_date": "20260716",
    "stck_cntg_hour": "091900",
    "stck_prpr": "2785",
    "stck_oprc": "2745",
    "stck_hgpr": "2805",
    "stck_lwpr": "2720",
    "cntg_vol": "112051",
    "acml_tr_pbmn": "17808658456"
  },
  {
    "stck_bsop_date": "20260716",
    "stck_cntg_hour": "092000",
    "stck_prpr": "2765",
    "stck_oprc": "2785",
    "stck_hgpr": "2795",
    "stck_lwpr": "2750",
    "cntg_vol": "96791",
    "acml_tr_pbmn": "18076624097"
  },
  {
    "stck_bsop_date": "20260716",
    "stck_cntg_hour": "092100",
    "stck_prpr": "2725",
    "stck_oprc": "2760",
    "stck_hgpr": "2785",
    "stck_lwpr": "2725",
    "cntg_vol": "104433",
    "acml_tr_pbmn": "18365038196"
  },
  {
    "stck_bsop_date": "20260716",
    "stck_cntg_hour": "092200",
    "stck_prpr": "2725",
    "stck_oprc": "2730",
    "stck_hgpr": "2755",
    "stck_lwpr": "2710",
    "cntg_vol": "85004",
    "acml_tr_pbmn": "18596582211"
  },
  {
    "stck_bsop_date": "20260716",
    "stck_cntg_hour": "092300",
    "stck_prpr": "2710",
    "stck_oprc": "2725",
    "stck_hgpr": "2730",
    "stck_lwpr": "2710",
    "cntg_vol": "70622",
    "acml_tr_pbmn": "18788465971"
  },
  {
    "stck_bsop_date": "20260716",
    "stck_cntg_hour": "092400",
    "stck_prpr": "2700",
    "stck_oprc": "2705",
    "stck_hgpr": "2710",
    "stck_lwpr": "2700",
    "cntg_vol": "88963",
    "acml_tr_pbmn": "19039082088"
  },
  {
    "stck_bsop_date": "20260716",
    "stck_cntg_hour": "092500",
    "stck_prpr": "2700",
    "stck_oprc": "2700",
    "stck_hgpr": "2700",
    "stck_lwpr": "2700",
    "cntg_vol": "0",
    "acml_tr_pbmn": "19039082088"
  },
  {
    "stck_bsop_date": "20260716",
    "stck_cntg_hour": "092600",
    "stck_prpr": "2660",
    "stck_oprc": "2700",
    "stck_hgpr": "2700",
    "stck_lwpr": "2650",
    "cntg_vol": "241654",
    "acml_tr_pbmn": "19685998418"
  },
  {
    "stck_bsop_date": "20260716",
    "stck_cntg_hour": "092700",
    "stck_prpr": "2685",
    "stck_oprc": "2665",
    "stck_hgpr": "2700",
    "stck_lwpr": "2650",
    "cntg_vol": "119507",
    "acml_tr_pbmn": "20005385770"
  },
  {
    "stck_bsop_date": "20260716",
    "stck_cntg_hour": "092800",
    "stck_prpr": "2680",
    "stck_oprc": "2690",
    "stck_hgpr": "2690",
    "stck_lwpr": "2665",
    "cntg_vol": "50518",
    "acml_tr_pbmn": "20140514991"
  },
  {
    "stck_bsop_date": "20260716",
    "stck_cntg_hour": "092900",
    "stck_prpr": "2685",
    "stck_oprc": "2680",
    "stck_hgpr": "2690",
    "stck_lwpr": "2675",
    "cntg_vol": "31616",
    "acml_tr_pbmn": "20225384399"
  },
  {
    "stck_bsop_date": "20260716",
    "stck_cntg_hour": "093000",
    "stck_prpr": "2695",
    "stck_oprc": "2690",
    "stck_hgpr": "2710",
    "stck_lwpr": "2680",
    "cntg_vol": "63022",
    "acml_tr_pbmn": "20395199138"
  },
  {
    "stck_bsop_date": "20260716",
    "stck_cntg_hour": "093100",
    "stck_prpr": "2740",
    "stck_oprc": "2700",
    "stck_hgpr": "2750",
    "stck_lwpr": "2685",
    "cntg_vol": "108879",
    "acml_tr_pbmn": "20690256072"
  },
  {
    "stck_bsop_date": "20260716",
    "stck_cntg_hour": "093200",
    "stck_prpr": "2715",
    "stck_oprc": "2745",
    "stck_hgpr": "2750",
    "stck_lwpr": "2700",
    "cntg_vol": "75181",
    "acml_tr_pbmn": "20895095152"
  },
  {
    "stck_bsop_date": "20260716",
    "stck_cntg_hour": "093300",
    "stck_prpr": "2720",
    "stck_oprc": "2710",
    "stck_hgpr": "2730",
    "stck_lwpr": "2700",
    "cntg_vol": "30696",
    "acml_tr_pbmn": "20978398462"
  },
  {
    "stck_bsop_date": "20260716",
    "stck_cntg_hour": "093400",
    "stck_prpr": "2705",
    "stck_oprc": "2720",
    "stck_hgpr": "2720",
    "stck_lwpr": "2700",
    "cntg_vol": "33152",
    "acml_tr_pbmn": "21068202707"
  },
  {
    "stck_bsop_date": "20260716",
    "stck_cntg_hour": "093500",
    "stck_prpr": "2715",
    "stck_oprc": "2700",
    "stck_hgpr": "2720",
    "stck_lwpr": "2700",
    "cntg_vol": "54717",
    "acml_tr_pbmn": "21216330659"
  },
  {
    "stck_bsop_date": "20260716",
    "stck_cntg_hour": "093600",
    "stck_prpr": "2685",
    "stck_oprc": "2720",
    "stck_hgpr": "2725",
    "stck_lwpr": "2685",
    "cntg_vol": "70100",
    "acml_tr_pbmn": "21405546233"
  },
  {
    "stck_bsop_date": "20260716",
    "stck_cntg_hour": "093700",
    "stck_prpr": "2680",
    "stck_oprc": "2690",
    "stck_hgpr": "2690",
    "stck_lwpr": "2675",
    "cntg_vol": "46536",
    "acml_tr_pbmn": "21530318528"
  },
  {
    "stck_bsop_date": "20260716",
    "stck_cntg_hour": "093800",
    "stck_prpr": "2680",
    "stck_oprc": "2680",
    "stck_hgpr": "2685",
    "stck_lwpr": "2670",
    "cntg_vol": "77068",
    "acml_tr_pbmn": "21736312775"
  },
  {
    "stck_bsop_date": "20260716",
    "stck_cntg_hour": "093900",
    "stck_prpr": "2695",
    "stck_oprc": "2670",
    "stck_hgpr": "2695",
    "stck_lwpr": "2665",
    "cntg_vol": "58864",
    "acml_tr_pbmn": "21893860345"
  },
  {
    "stck_bsop_date": "20260716",
    "stck_cntg_hour": "094000",
    "stck_prpr": "2700",
    "stck_oprc": "2695",
    "stck_hgpr": "2700",
    "stck_lwpr": "2685",
    "cntg_vol": "28798",
    "acml_tr_pbmn": "21971425720"
  },
  {
    "stck_bsop_date": "20260716",
    "stck_cntg_hour": "094100",
    "stck_prpr": "2705",
    "stck_oprc": "2700",
    "stck_hgpr": "2710",
    "stck_lwpr": "2695",
    "cntg_vol": "24928",
    "acml_tr_pbmn": "22038743413"
  },
  {
    "stck_bsop_date": "20260716",
    "stck_cntg_hour": "094200",
    "stck_prpr": "2720",
    "stck_oprc": "2705",
    "stck_hgpr": "2725",
    "stck_lwpr": "2690",
    "cntg_vol": "133429",
    "acml_tr_pbmn": "22399511723"
  },
  {
    "stck_bsop_date": "20260716",
    "stck_cntg_hour": "094300",
    "stck_prpr": "2730",
    "stck_oprc": "2720",
    "stck_hgpr": "2735",
    "stck_lwpr": "2715",
    "cntg_vol": "12379",
    "acml_tr_pbmn": "22433266623"
  },
  {
    "stck_bsop_date": "20260716",
    "stck_cntg_hour": "095600",
    "stck_prpr": "2865",
    "stck_oprc": "2905",
    "stck_hgpr": "2920",
    "stck_lwpr": "2835",
    "cntg_vol": "328054",
    "acml_tr_pbmn": "27811765587"
  },
  {
    "stck_bsop_date": "20260716",
    "stck_cntg_hour": "095700",
    "stck_prpr": "2880",
    "stck_oprc": "2865",
    "stck_hgpr": "2900",
    "stck_lwpr": "2865",
    "cntg_vol": "193818",
    "acml_tr_pbmn": "28371041007"
  },
  {
    "stck_bsop_date": "20260716",
    "stck_cntg_hour": "095800",
    "stck_prpr": "2905",
    "stck_oprc": "2875",
    "stck_hgpr": "2915",
    "stck_lwpr": "2850",
    "cntg_vol": "221673",
    "acml_tr_pbmn": "29011283069"
  },
  {
    "stck_bsop_date": "20260716",
    "stck_cntg_hour": "095900",
    "stck_prpr": "2935",
    "stck_oprc": "2910",
    "stck_hgpr": "2950",
    "stck_lwpr": "2885",
    "cntg_vol": "526931",
    "acml_tr_pbmn": "30552947105"
  },
  {
    "stck_bsop_date": "20260716",
    "stck_cntg_hour": "100000",
    "stck_prpr": "2900",
    "stck_oprc": "2930",
    "stck_hgpr": "2950",
    "stck_lwpr": "2900",
    "cntg_vol": "326423",
    "acml_tr_pbmn": "31510536129"
  },
  {
    "stck_bsop_date": "20260716",
    "stck_cntg_hour": "100100",
    "stck_prpr": "2920",
    "stck_oprc": "2905",
    "stck_hgpr": "2940",
    "stck_lwpr": "2900",
    "cntg_vol": "165384",
    "acml_tr_pbmn": "31993244149"
  },
  {
    "stck_bsop_date": "20260716",
    "stck_cntg_hour": "100200",
    "stck_prpr": "2935",
    "stck_oprc": "2920",
    "stck_hgpr": "2940",
    "stck_lwpr": "2905",
    "cntg_vol": "141218",
    "acml_tr_pbmn": "32405319111"
  },
  {
    "stck_bsop_date": "20260716",
    "stck_cntg_hour": "100300",
    "stck_prpr": "2910",
    "stck_oprc": "2935",
    "stck_hgpr": "2935",
    "stck_lwpr": "2905",
    "cntg_vol": "136774",
    "acml_tr_pbmn": "32803254306"
  },
  {
    "stck_bsop_date": "20260716",
    "stck_cntg_hour": "100400",
    "stck_prpr": "2920",
    "stck_oprc": "2905",
    "stck_hgpr": "2955",
    "stck_lwpr": "2900",
    "cntg_vol": "382157",
    "acml_tr_pbmn": "33923921131"
  },
  {
    "stck_bsop_date": "20260716",
    "stck_cntg_hour": "100500",
    "stck_prpr": "2910",
    "stck_oprc": "2930",
    "stck_hgpr": "2930",
    "stck_lwpr": "2900",
    "cntg_vol": "125082",
    "acml_tr_pbmn": "34287847521"
  },
  {
    "stck_bsop_date": "20260716",
    "stck_cntg_hour": "100600",
    "stck_prpr": "2875",
    "stck_oprc": "2910",
    "stck_hgpr": "2920",
    "stck_lwpr": "2860",
    "cntg_vol": "209711",
    "acml_tr_pbmn": "34893631971"
  },
  {
    "stck_bsop_date": "20260716",
    "stck_cntg_hour": "100700",
    "stck_prpr": "2835",
    "stck_oprc": "2880",
    "stck_hgpr": "2885",
    "stck_lwpr": "2820",
    "cntg_vol": "264704",
    "acml_tr_pbmn": "35646706271"
  },
  {
    "stck_bsop_date": "20260716",
    "stck_cntg_hour": "100800",
    "stck_prpr": "2865",
    "stck_oprc": "2835",
    "stck_hgpr": "2870",
    "stck_lwpr": "2830",
    "cntg_vol": "79801",
    "acml_tr_pbmn": "35873924539"
  },
  {
    "stck_bsop_date": "20260716",
    "stck_cntg_hour": "100900",
    "stck_prpr": "2865",
    "stck_oprc": "2865",
    "stck_hgpr": "2880",
    "stck_lwpr": "2855",
    "cntg_vol": "69202",
    "acml_tr_pbmn": "36072121679"
  },
  {
    "stck_bsop_date": "20260716",
    "stck_cntg_hour": "101000",
    "stck_prpr": "2875",
    "stck_oprc": "2865",
    "stck_hgpr": "2875",
    "stck_lwpr": "2855",
    "cntg_vol": "45127",
    "acml_tr_pbmn": "36201517814"
  },
  {
    "stck_bsop_date": "20260716",
    "stck_cntg_hour": "101100",
    "stck_prpr": "2855",
    "stck_oprc": "2870",
    "stck_hgpr": "2890",
    "stck_lwpr": "2850",
    "cntg_vol": "88718",
    "acml_tr_pbmn": "36455837456"
  },
  {
    "stck_bsop_date": "20260716",
    "stck_cntg_hour": "101200",
    "stck_prpr": "2840",
    "stck_oprc": "2855",
    "stck_hgpr": "2860",
    "stck_lwpr": "2825",
    "cntg_vol": "85098",
    "acml_tr_pbmn": "36697736201"
  },
  {
    "stck_bsop_date": "20260716",
    "stck_cntg_hour": "101300",
    "stck_prpr": "2845",
    "stck_oprc": "2850",
    "stck_hgpr": "2855",
    "stck_lwpr": "2815",
    "cntg_vol": "106949",
    "acml_tr_pbmn": "37000746966"
  },
  {
    "stck_bsop_date": "20260716",
    "stck_cntg_hour": "101400",
    "stck_prpr": "2810",
    "stck_oprc": "2840",
    "stck_hgpr": "2845",
    "stck_lwpr": "2805",
    "cntg_vol": "114725",
    "acml_tr_pbmn": "37323750576"
  },
  {
    "stck_bsop_date": "20260716",
    "stck_cntg_hour": "101500",
    "stck_prpr": "2830",
    "stck_oprc": "2810",
    "stck_hgpr": "2835",
    "stck_lwpr": "2810",
    "cntg_vol": "68730",
    "acml_tr_pbmn": "37517691434"
  },
  {
    "stck_bsop_date": "20260716",
    "stck_cntg_hour": "101600",
    "stck_prpr": "2860",
    "stck_oprc": "2830",
    "stck_hgpr": "2860",
    "stck_lwpr": "2830",
    "cntg_vol": "109380",
    "acml_tr_pbmn": "37829582229"
  },
  {
    "stck_bsop_date": "20260716",
    "stck_cntg_hour": "101700",
    "stck_prpr": "2865",
    "stck_oprc": "2855",
    "stck_hgpr": "2875",
    "stck_lwpr": "2850",
    "cntg_vol": "66874",
    "acml_tr_pbmn": "38020633542"
  },
  {
    "stck_bsop_date": "20260716",
    "stck_cntg_hour": "101800",
    "stck_prpr": "2865",
    "stck_oprc": "2875",
    "stck_hgpr": "2885",
    "stck_lwpr": "2855",
    "cntg_vol": "82566",
    "acml_tr_pbmn": "38257413742"
  },
  {
    "stck_bsop_date": "20260716",
    "stck_cntg_hour": "101900",
    "stck_prpr": "2840",
    "stck_oprc": "2855",
    "stck_hgpr": "2865",
    "stck_lwpr": "2840",
    "cntg_vol": "57953",
    "acml_tr_pbmn": "38422756487"
  },
  {
    "stck_bsop_date": "20260716",
    "stck_cntg_hour": "102000",
    "stck_prpr": "2840",
    "stck_oprc": "2840",
    "stck_hgpr": "2845",
    "stck_lwpr": "2835",
    "cntg_vol": "71669",
    "acml_tr_pbmn": "38626307147"
  },
  {
    "stck_bsop_date": "20260716",
    "stck_cntg_hour": "102100",
    "stck_prpr": "2840",
    "stck_oprc": "2840",
    "stck_hgpr": "2845",
    "stck_lwpr": "2835",
    "cntg_vol": "71055",
    "acml_tr_pbmn": "38828020887"
  },
  {
    "stck_bsop_date": "20260716",
    "stck_cntg_hour": "102200",
    "stck_prpr": "2810",
    "stck_oprc": "2845",
    "stck_hgpr": "2845",
    "stck_lwpr": "2810",
    "cntg_vol": "80917",
    "acml_tr_pbmn": "39056505977"
  },
  {
    "stck_bsop_date": "20260716",
    "stck_cntg_hour": "102300",
    "stck_prpr": "2830",
    "stck_oprc": "2810",
    "stck_hgpr": "2835",
    "stck_lwpr": "2805",
    "cntg_vol": "50210",
    "acml_tr_pbmn": "39197973958"
  },
  {
    "stck_bsop_date": "20260716",
    "stck_cntg_hour": "102400",
    "stck_prpr": "2820",
    "stck_oprc": "2825",
    "stck_hgpr": "2830",
    "stck_lwpr": "2815",
    "cntg_vol": "27468",
    "acml_tr_pbmn": "39275502728"
  },
  {
    "stck_bsop_date": "20260716",
    "stck_cntg_hour": "102500",
    "stck_prpr": "2810",
    "stck_oprc": "2815",
    "stck_hgpr": "2820",
    "stck_lwpr": "2810",
    "cntg_vol": "15338",
    "acml_tr_pbmn": "39318686348"
  },
  {
    "stck_bsop_date": "20260715",
    "stck_cntg_hour": "152500",
    "stck_prpr": "2810",
    "stck_oprc": "2810",
    "stck_hgpr": "2810",
    "stck_lwpr": "2810",
    "cntg_vol": "0",
    "acml_tr_pbmn": "131534002629"
  },
  {
    "stck_bsop_date": "20260715",
    "stck_cntg_hour": "152600",
    "stck_prpr": "2810",
    "stck_oprc": "2810",
    "stck_hgpr": "2810",
    "stck_lwpr": "2810",
    "cntg_vol": "0",
    "acml_tr_pbmn": "131534002629"
  },
  {
    "stck_bsop_date": "20260715",
    "stck_cntg_hour": "152700",
    "stck_prpr": "2810",
    "stck_oprc": "2810",
    "stck_hgpr": "2810",
    "stck_lwpr": "2810",
    "cntg_vol": "0",
    "acml_tr_pbmn": "131534002629"
  },
  {
    "stck_bsop_date": "20260715",
    "stck_cntg_hour": "152800",
    "stck_prpr": "2810",
    "stck_oprc": "2810",
    "stck_hgpr": "2810",
    "stck_lwpr": "2810",
    "cntg_vol": "0",
    "acml_tr_pbmn": "131534002629"
  },
  {
    "stck_bsop_date": "20260715",
    "stck_cntg_hour": "152900",
    "stck_prpr": "2810",
    "stck_oprc": "2810",
    "stck_hgpr": "2810",
    "stck_lwpr": "2810",
    "cntg_vol": "0",
    "acml_tr_pbmn": "131534002629"
  },
  {
    "stck_bsop_date": "20260715",
    "stck_cntg_hour": "153000",
    "stck_prpr": "2825",
    "stck_oprc": "2825",
    "stck_hgpr": "2825",
    "stck_lwpr": "2825",
    "cntg_vol": "184821",
    "acml_tr_pbmn": "132056121954"
  }
]