[
  {
    "stck_bsop_date": "20260721",
    "stck_cntg_hour": "095100",
    "stck_prpr": "36010",
    "stck_oprc": "35995",
    "stck_hgpr": "36040",
    "stck_lwpr": "35895",
    "cntg_vol": "28195",
    "acml_tr_pbmn": "118754077759"
  },
  {
    "stck_bsop_date": "20260721",
    "stck_cntg_hour": "095200",
    "stck_prpr": "35975",
    "stck_oprc": "36010",
    "stck_hgpr": "36030",
    "stck_lwpr": "35910",
    "cntg_vol": "56015",
    "acml_tr_pbmn": "120768267998"
  },
  {
    "stck_bsop_date": "20260721",
    "stck_cntg_hour": "095300",
    "stck_prpr": "36015",
    "stck_oprc": "35980",
    "stck_hgpr": "36015",
    "stck_lwpr": "35920",
    "cntg_vol": "36980",
    "acml_tr_pbmn": "122097946404"
  },
  {
    "stck_bsop_date": "20260721",
    "stck_cntg_hour": "095400",
    "stck_prpr": "35925",
    "stck_oprc": "36015",
    "stck_hgpr": "36035",
    "stck_lwpr": "35900",
    "cntg_vol": "28285",
    "acml_tr_pbmn": "123115437869"
  },
  {
    "stck_bsop_date": "20260721",
    "stck_cntg_hour": "095500",
    "stck_prpr": "35835",
    "stck_oprc": "35915",
    "stck_hgpr": "36005",
    "stck_lwpr": "35835",
    "cntg_vol": "42993",
    "acml_tr_pbmn": "124660147614"
  },
  {
    "stck_bsop_date": "20260721",
    "stck_cntg_hour": "095600",
    "stck_prpr": "35800",
    "stck_oprc": "35830",
    "stck_hgpr": "35850",
    "stck_lwpr": "35770",
    "cntg_vol": "61934",
    "acml_tr_pbmn": "126878557509"
  },
  {
    "stck_bsop_date": "20260721",
    "stck_cntg_hour": "095700",
    "stck_prpr": "35825",
    "stck_oprc": "35805",
    "stck_hgpr": "35850",
    "stck_lwpr": "35730",
    "cntg_vol": "34964",
    "acml_tr_pbmn": "128130335204"
  },
  {
    "stck_bsop_date": "20260721",
    "stck_cntg_hour": "095800",
    "stck_prpr": "35675",
    "stck_oprc": "35830",
    "stck_hgpr": "35830",
    "stck_lwpr": "35645",
    "cntg_vol": "29279",
    "acml_tr_pbmn": "129176328479"
  },
  {
    "stck_bsop_date": "20260721",
    "stck_cntg_hour": "095900",
    "stck_prpr": "35605",
    "stck_oprc": "35680",
    "stck_hgpr": "35690",
    "stck_lwpr": "35595",
    "cntg_vol": "30470",
    "acml_tr_pbmn": "130261817549"
  },
  {
    "stck_bsop_date": "20260721",
    "stck_cntg_hour": "100000",
    "stck_prpr": "35590",
    "stck_oprc": "35605",
    "stck_hgpr": "35625",
    "stck_lwpr": "35550",
    "cntg_vol": "39684",
    "acml_tr_pbmn": "131674291661"
  },
  {
    "stck_bsop_date": "20260721",
    "stck_cntg_hour": "100100",
    "stck_prpr": "35575",
    "stck_oprc": "35595",
    "stck_hgpr": "35605",
    "stck_lwpr": "35505",
    "cntg_vol": "28150",
    "acml_tr_pbmn": "132675155970"
  },
  {
    "stck_bsop_date": "20260721",
    "stck_cntg_hour": "100200",
    "stck_prpr": "35590",
    "stck_oprc": "35565",
    "stck_hgpr": "35680",
    "stck_lwpr": "35495",
    "cntg_vol": "44567",
    "acml_tr_pbmn": "134260896620"
  },
  {
    "stck_bsop_date": "20260721",
    "stck_cntg_hour": "100300",
    "stck_prpr": "35675",
    "stck_oprc": "35590",
    "stck_hgpr": "35710",
    "stck_lwpr": "35485",
    "cntg_vol": "68980",
    "acml_tr_pbmn": "136716879297"
  },
  {
    "stck_bsop_date": "20260721",
    "stck_cntg_hour": "100400",
    "stck_prpr": "35970",
    "stck_oprc": "35695",
    "stck_hgpr": "35970",
    "stck_lwpr": "35670",
    "cntg_vol": "75359",
    "acml_tr_pbmn": "139413234197"
  },
  {
    "stck_bsop_date": "20260721",
    "stck_cntg_hour": "100500",
    "stck_prpr": "36060",
    "stck_oprc": "35965",
    "stck_hgpr": "36085",
    "stck_lwpr": "35895",
    "cntg_vol": "124943",
    "acml_tr_pbmn": "143908296947"
  },
  {
    "stck_bsop_date": "20260721",
    "stck_cntg_hour": "100600",
    "stck_prpr": "36095",
    "stck_oprc": "36040",
    "stck_hgpr": "36165",
    "stck_lwpr": "36040",
    "cntg_vol": "59303",
    "acml_tr_pbmn": "146049800542"
  },
  {
    "stck_bsop_date": "20260721",
    "stck_cntg_hour": "100700",
    "stck_prpr": "36155",
    "stck_oprc": "36090",
    "stck_hgpr": "36160",
    "stck_lwpr": "36050",
    "cntg_vol": "60951",
    "acml_tr_pbmn": "148249893767"
  },
  {
    "stck_bsop_date": "20260721",
    "stck_cntg_hour": "100800",
    "stck_prpr": "36215",
    "stck_oprc": "36150",
    "stck_hgpr": "36240",
    "stck_lwpr": "36110",
    "cntg_vol": "84238",
    "acml_tr_pbmn": "151296836194"
  },
  {
    "stck_bsop_date": "20260721",
    "stck_cntg_hour": "100900",
    "stck_prpr": "36260",
    "stck_oprc": "36220",
    "stck_hgpr": "36315",
    "stck_lwpr": "36195",
    "cntg_vol": "46946",
    "acml_tr_pbmn": "152998818805"
  },
  {
    "stck_bsop_date": "20260721",
    "stck_cntg_hour": "101000",
    "stck_prpr": "36210",
    "stck_oprc": "36250",
    "stck_hgpr": "36300",
    "stck_lwpr": "36140",
    "cntg_vol": "49316",
    "acml_tr_pbmn": "154785473515"
  },
  {
    "stck_bsop_date": "20260721",
    "stck_cntg_hour": "101100",
    "stck_prpr": "36200",
    "stck_oprc": "36220",
    "stck_hgpr": "36245",
    "stck_lwpr": "36155",
    "cntg_vol": "31464",
    "acml_tr_pbmn": "155924693637"
  },
  {
    "stck_bsop_date": "20260721",
    "stck_cntg_hour": "101200",
    "stck_prpr": "36305",
    "stck_oprc": "36210",
    "stck_hgpr": "36310",
    "stck_lwpr": "36155",
    "cntg_vol": "76493",
    "acml_tr_pbmn": "158694834435"
  },
  {
    "stck_bsop_date": "20260721",
    "stck_cntg_hour": "101300",
    "stck_prpr": "36300",
    "stck_oprc": "36300",
    "stck_hgpr": "36345",
    "stck_lwpr": "36270",
    "cntg_vol": "102075",
    "acml_tr_pbmn": "162402003310"
  },
  {
    "stck_bsop_date": "20260721",
    "stck_cntg_hour": "101400",
    "stck_prpr": "36320",
    "stck_oprc": "36300",
    "stck_hgpr": "36415",
    "stck_lwpr": "36275",
    "cntg_vol": "59156",
    "acml_tr_pbmn": "164552429877"
  },
  {
    "stck_bsop_date": "20260721",
    "stck_cntg_hour": "101500",
    "stck_prpr": "36330",
    "stck_oprc": "36320",
    "stck_hgpr": "36430",
    "stck_lwpr": "36300",
    "cntg_vol": "36739",
    "acml_tr_pbmn": "165887853102"
  },
  {
    "stck_bsop_date": "20260721",
    "stck_cntg_hour": "101600",
    "stck_prpr": "36290",
    "stck_oprc": "36330",
    "stck_hgpr": "36355",
    "stck_lwpr": "36260",
    "cntg_vol": "118459",
    "acml_tr_pbmn": "170187435672"
  },
  {
    "stck_bsop_date": "20260721",
    "stck_cntg_hour": "101700",
    "stck_prpr": "36125",
    "stck_oprc": "36285",
    "stck_hgpr": "36335",
    "stck_lwpr": "36100",
    "cntg_vol": "75823",
    "acml_tr_pbmn": "172936077269"
  },
  {
    "stck_bsop_date": "20260721",
    "stck_cntg_hour": "101800",
    "stck_prpr": "36115",
    "stck_oprc": "36115",
    "stck_hgpr": "36140",
    "stck_lwpr": "36055",
    "cntg_vol": "61251",
    "acml_tr_pbmn": "175147507886"
  },
  {
    "stck_bsop_date": "20260721",
    "stck_cntg_hour": "101900",
    "stck_prpr": "36230",
    "stck_oprc": "36110",
    "stck_hgpr": "36245",
    "stck_lwpr": "36015",
    "cntg_vol": "51611",
    "acml_tr_pbmn": "177012021056"
  },
  {
    "stck_bsop_date": "20260721",
    "stck_cntg_hour": "102000",
    "stck_prpr": "36285",
    "stck_oprc": "36230",
    "stck_hgpr": "36320",
    "stck_lwpr": "36230",
    "cntg_vol": "10298",
    "acml_tr_pbmn": "177385625721"
  },
  {
    "stck_bsop_date": "20260721",
    "stck_cntg_hour": "102100",
    "stck_prpr": "36130",
    "stck_oprc": "36295",
    "stck_hgpr": "36305",
    "stck_lwpr": "36115",
    "cntg_vol": "25704",
    "acml_tr_pbmn": "181612150761"
  },
  {
    "stck_bsop_date": "20260721",
    "stck_cntg_hour": "102200",
    "stck_prpr": "36195",
    "stck_oprc": "36130",
    "stck_hgpr": "36225",
    "stck_lwpr": "36080",
    "cntg_vol": "22800",
    "acml_tr_pbmn": "182436394591"
  },
  {
    "stck_bsop_date": "20260721",
    "stck_cntg_hour": "102300",
    "stck_prpr": "36130",
    "stck_oprc": "36195",
    "stck_hgpr": "36215",
    "stck_lwpr": "36095",
    "cntg_vol": "17997",
    "acml_tr_pbmn": "183086793336"
  },
  {
    "stck_bsop_date": "20260721",
    "stck_cntg_hour": "102400",
    "stck_prpr": "36215",
    "stck_oprc": "36145",
    "stck_hgpr": "36305",
    "stck_lwpr": "36130",
    "cntg_vol": "45070",
    "acml_tr_pbmn": "184719602606"
  },
  {
    "stck_bsop_date": "20260721",
    "stck_cntg_hour": "102500",
    "stck_prpr": "36240",
    "stck_oprc": "36230",
    "stck_hgpr": "36275",
    "stck_lwpr": "36175",
    "cntg_vol": "29485",
    "acml_tr_pbmn": "185788094277"
  },
  {
    "stck_bsop_date": "20260721",
    "stck_cntg_hour": "102600",
    "stck_prpr": "36160",
    "stck_oprc": "36250",
    "stck_hgpr": "36250",
    "stck_lwpr": "36100",
    "cntg_vol": "47603",
    "acml_tr_pbmn": "187509464283"
  },
  {
    "stck_bsop_date": "20260721",
    "stck_cntg_hour": "102700",
    "stck_prpr": "36250",
    "stck_oprc": "36155",
    "stck_hgpr": "36325",
    "stck_lwpr": "36145",
    "cntg_vol": "38363",
    "acml_tr_pbmn": "188900377968"
  },
  {
    "stck_bsop_date": "20260721",
    "stck_cntg_hour": "102800",
    "stck_prpr": "36290",
    "stck_oprc": "36250",
    "stck_hgpr": "36330",
    "stck_lwpr": "36240",
    "cntg_vol": "35461",
    "acml_tr_pbmn": "190186902117"
  },
  {
    "stck_bsop_date": "20260721",
    "stck_cntg_hour": "102900",
    "stck_prpr": "36330",
    "stck_oprc": "36300",
    "stck_hgpr": "36330",
    "stck_lwpr": "36290",
    "cntg_vol": "3643",
    "acml_tr_pbmn": "190319223042"
  },
  {
    "stck_bsop_date": "20260721",
    "stck_cntg_hour": "103000",
    "stck_prpr": "36425",
    "stck_oprc": "36280",
    "stck_hgpr": "36430",
    "stck_lwpr": "36265",
    "cntg_vol": "47535",
    "acml_tr_pbmn": "192960024817"
  },
  {
    "stck_bsop_date": "20260721",
    "stck_cntg_hour": "103100",
    "stck_prpr": "36540",
    "stck_oprc": "36420",
    "stck_hgpr": "36545",
    "stck_lwpr": "36410",
    "cntg_vol": "87064",
    "acml_tr_pbmn": "196136089112"
  },
  {
    "stck_bsop_date": "20260721",
    "stck_cntg_hour": "103200",
    "stck_prpr": "36625",
    "stck_oprc": "36545",
    "stck_hgpr": "36625",
    "stck_lwpr": "36540",
    "cntg_vol": "32652",
    "acml_tr_pbmn": "197330395516"
  },
  {
    "stck_bsop_date": "20260721",
    "stck_cntg_hour": "103300",
    "stck_prpr": "36665",
    "stck_oprc": "36610",
    "stck_hgpr": "36670",
    "stck_lwpr": "36550",
    "cntg_vol": "66503",
    "acml_tr_pbmn": "199764183296"
  },
  {
    "stck_bsop_date": "20260721",
    "stck_cntg_hour": "103400",
    "stck_prpr": "36690",
    "stck_oprc": "36665",
    "stck_hgpr": "36695",
    "stck_lwpr": "36635",
    "cntg_vol": "29062",
    "acml_tr_pbmn": "200829715726"
  },
  {
    "stck_bsop_date": "20260721",
    "stck_cntg_hour": "103500",
    "stck_prpr": "36635",
    "stck_oprc": "36685",
    "stck_hgpr": "36695",
    "stck_lwpr": "36615",
    "cntg_vol": "54503",
    "acml_tr_pbmn": "202827100521"
  },
  {
    "stck_bsop_date": "20260721",
    "stck_cntg_hour": "103600",
    "stck_prpr": "36705",
    "stck_oprc": "36635",
    "stck_hgpr": "36705",
    "stck_lwpr": "36590",
    "cntg_vol": "63891",
    "acml_tr_pbmn": "205168556651"
  },
  {
    "stck_bsop_date": "20260721",
    "stck_cntg_hour": "103700",
    "stck_prpr": "36765",
    "stck_oprc": "36710",
    "stck_hgpr": "36780",
    "stck_lwpr": "36660",
    "cntg_vol": "40447",
    "acml_tr_pbmn": "206653314366"
  },
  {
    "stck_bsop_date": "20260721",
    "stck_cntg_hour": "103800",
    "stck_prpr": "36645",
    "stck_oprc": "36755",
    "stck_hgpr": "36760",
    "stck_lwpr": "36630",
    "cntg_vol": "42475",
    "acml_tr_pbmn": "208211842666"
  },
  {
    "stck_bsop_date": "20260721",
    "stck_cntg_hour": "103900",
    "stck_prpr": "36640",
    "stck_oprc": "36640",
    "stck_hgpr": "36650",
    "stck_lwpr": "36620",
    "cntg_vol": "1780",
    "acml_tr_pbmn": "208277050596"
  },
  {
    "stck_bsop_date": "20260721",
    "stck_cntg_hour": "104000",
    "stck_prpr": "36690",
    "stck_oprc": "36620",
    "stck_hgpr": "36695",
    "stck_lwpr": "36505",
    "cntg_vol": "63306",
    "acml_tr_pbmn": "211373764750"
  },
  {
    "stck_bsop_date": "20260721",
    "stck_cntg_hour": "104100",
    "stck_prpr": "36585",
    "stck_oprc": "36685",
    "stck_hgpr": "36695",
    "stck_lwpr": "36565",
    "cntg_vol": "83448",
    "acml_tr_pbmn": "214430010611"
  },
  {
    "stck_bsop_date": "20260721",
    "stck_cntg_hour": "104200",
    "stck_prpr": "36580",
    "stck_oprc": "36585",
    "stck_hgpr": "36640",
    "stck_lwpr": "36560",
    "cntg_vol": "22801",
    "acml_tr_pbmn": "215264394591"
  },
  {
    "stck_bsop_date": "20260721",
    "stck_cntg_hour": "104300",
    "stck_prpr": "36530",
    "stck_oprc": "36575",
    "stck_hgpr": "36600",
    "stck_lwpr": "36515",
    "cntg_vol": "26060",
    "acml_tr_pbmn": "216216846187"
  },
  {
    "stck_bsop_date": "20260721",
    "stck_cntg_hour": "104400",
    "stck_prpr": "36510",
    "stck_oprc": "36535",
    "stck_hgpr": "36560",
    "stck_lwpr": "36480",
    "cntg_vol": "50546",
    "acml_tr_pbmn": "218062697987"
  },
  {
    "stck_bsop_date": "20260721",
    "stck_cntg_hour": "104500",
    "stck_prpr": "36470",
    "stck_oprc": "36510",
    "stck_hgpr": "36530",
    "stck_lwpr": "36430",
    "cntg_vol": "54986",
    "acml_tr_pbmn": "220068488189"
  },
  {
    "stck_bsop_date": "20260721",
    "stck_cntg_hour": "104600",
    "stck_prpr": "36465",
    "stck_oprc": "36475",
    "stck_hgpr": "36485",
    "stck_lwpr": "36425",
    "cntg_vol": "21518",
    "acml_tr_pbmn": "220852968441"
  },
  {
    "stck_bsop_date": "20260721",
    "stck_cntg_hour": "104700",
    "stck_prpr": "36520",
    "stck_oprc": "36465",
    "stck_hgpr": "36565",
    "stck_lwpr": "36465",
    "cntg_vol": "60383",
    "acml_tr_pbmn": "223058369651"
  },
  {
    "stck_bsop_date": "20260721",
    "stck_cntg_hour": "104800",
    "stck_prpr": "36530",
    "stck_oprc": "36515",
    "stck_hgpr": "36530",
    "stck_lwpr": "36515",
    "cntg_vol": "1342",
    "acml_tr_pbmn": "223107385456"
  },
  {
    "stck_bsop_date": "20260721",
    "stck_cntg_hour": "104900",
    "stck_prpr": "36640",
    "stck_oprc": "36585",
    "stck_hgpr": "36670",
    "stck_lwpr": "36575",
    "cntg_vol": "48392",
    "acml_tr_pbmn": "227589219906"
  },
  {
    "stck_bsop_date": "20260721",
    "stck_cntg_hour": "105000",
    "stck_prpr": "36555",
    "stck_oprc": "36655",
    "stck_hgpr": "36675",
    "stck_lwpr": "36540",
    "cntg_vol": "77291",
    "acml_tr_pbmn": "230418008481"
  },
  {
    "stck_bsop_date": "20260721",
    "stck_cntg_hour": "105100",
    "stck_prpr": "36345",
    "stck_oprc": "36555",
    "stck_hgpr": "36555",
    "stck_lwpr": "36345",
    "cntg_vol": "72274",
    "acml_tr_pbmn": "233051407066"
  },
  {
    "stck_bsop_date": "20260721",
    "stck_cntg_hour": "105200",
    "stck_prpr": "36350",
    "stck_oprc": "36355",
    "stck_hgpr": "36385",
    "stck_lwpr": "36325",
    "cntg_vol": "32809",
    "acml_tr_pbmn": "234244229958"
  },
  {
    "stck_bsop_date": "20260721",
    "stck_cntg_hour": "105300",
    "stck_prpr": "36435",
    "stck_oprc": "36350",
    "stck_hgpr": "36450",
    "stck_lwpr": "36290",
    "cntg_vol": "58643",
    "acml_tr_pbmn": "236375710825"
  },
  {
    "stck_bsop_date": "20260721",
    "stck_cntg_hour": "105400",
    "stck_prpr": "36480",
    "stck_oprc": "36435",
    "stck_hgpr": "36510",
    "stck_lwpr": "36390",
    "cntg_vol": "96438",
    "acml_tr_pbmn": "239890091170"
  },
  {
    "stck_bsop_date": "20260721",
    "stck_cntg_hour": "105500",
    "stck_prpr": "36365",
    "stck_oprc": "36480",
    "stck_hgpr": "36485",
    "stck_lwpr": "36285",
    "cntg_vol": "105239",
    "acml_tr_pbmn": "243718825562"
  },
  {
    "stck_bsop_date": "20260721",
    "stck_cntg_hour": "105600",
    "stck_prpr": "36310",
    "stck_oprc": "36385",
    "stck_hgpr": "36395",
    "stck_lwpr": "36290",
    "cntg_vol": "36158",
    "acml_tr_pbmn": "245033168819"
  },
  {
    "stck_bsop_date": "20260721",
    "stck_cntg_hour": "105700",
    "stck_prpr": "36230",
    "stck_oprc": "36325",
    "stck_hgpr": "36330",
    "stck_lwpr": "36215",
    "cntg_vol": "23360",
    "acml_tr_pbmn": "245880268004"
  },
  {
    "stck_bsop_date": "20260721",
    "stck_cntg_hour": "105800",
    "stck_prpr": "36160",
    "stck_oprc": "36220",
    "stck_hgpr": "36230",
    "stck_lwpr": "36145",
    "cntg_vol": "42956",
    "acml_tr_pbmn": "247587636283"
  },
  {
    "stck_bsop_date": "20260721",
    "stck_cntg_hour": "105900",
    "stck_prpr": "36290",
    "stck_oprc": "36155",
    "stck_hgpr": "36290",
    "stck_lwpr": "36130",
    "cntg_vol": "39431",
    "acml_tr_pbmn": "249015855219"
  },
  {
    "stck_bsop_date": "20260721",
    "stck_cntg_hour": "110000",
    "stck_prpr": "36340",
    "stck_oprc": "36290",
    "stck_hgpr": "36365",
    "stck_lwpr": "36230",
    "cntg_vol": "54057",
    "acml_tr_pbmn": "250977129134"
  },
  {
    "stck_bsop_date": "20260721",
    "stck_cntg_hour": "110100",
    "stck_prpr": "36290",
    "stck_oprc": "36335",
    "stck_hgpr": "36385",
    "stck_lwpr": "36250",
    "cntg_vol": "41598",
    "acml_tr_pbmn": "252488246336"
  },
  {
    "stck_bsop_date": "20260721",
    "stck_cntg_hour": "110200",
    "stck_prpr": "36405",
    "stck_oprc": "36275",
    "stck_hgpr": "36445",
    "stck_lwpr": "36235",
    "cntg_vol": "68953",
    "acml_tr_pbmn": "254995280209"
  },
  {
    "stck_bsop_date": "20260721",
    "stck_cntg_hour": "110300",
    "stck_prpr": "36470",
    "stck_oprc": "36415",
    "stck_hgpr": "36520",
    "stck_lwpr": "36355",
    "cntg_vol": "65671",
    "acml_tr_pbmn": "257388871739"
  },
  {
    "stck_bsop_date": "20260721",
    "stck_cntg_hour": "110400",
    "stck_prpr": "36455",
    "stck_oprc": "36475",
    "stck_hgpr": "36515",
    "stck_lwpr": "36395",
    "cntg_vol": "51683",
    "acml_tr_pbmn": "259273684964"
  },
  {
    "stck_bsop_date": "20260721",
    "stck_cntg_hour": "110500",
    "stck_prpr": "36495",
    "stck_oprc": "36465",
    "stck_hgpr": "36520",
    "stck_lwpr": "36410",
    "cntg_vol": "43386",
    "acml_tr_pbmn": "260856217144"
  },
  {
    "stck_bsop_date": "20260721",
    "stck_cntg_hour": "110600",
    "stck_prpr": "36510",
    "stck_oprc": "36490",
    "stck_hgpr": "36515",
    "stck_lwpr": "36490",
    "cntg_vol": "519",
    "acml_tr_pbmn": "260875156794"
  },
  {
    "stck_bsop_date": "20260721",
    "stck_cntg_hour": "110700",
    "stck_prpr": "36375",
    "stck_oprc": "36420",
    "stck_hgpr": "36420",
    "stck_lwpr": "36330",
    "cntg_vol": "31995",
    "acml_tr_pbmn": "264748240554"
  },
  {
    "stck_bsop_date": "20260721",
    "stck_cntg_hour": "110800",
    "stck_prpr": "36275",
    "stck_oprc": "36375",
    "stck_hgpr": "36375",
    "stck_lwpr": "36260",
    "cntg_vol": "21868",
    "acml_tr_pbmn": "265542653279"
  },
  {
    "stck_bsop_date": "20260721",
    "stck_cntg_hour": "110900",
    "stck_prpr": "36125",
    "stck_oprc": "36275",
    "stck_hgpr": "36285",
    "stck_lwpr": "36125",
    "cntg_vol": "39217",
    "acml_tr_pbmn": "266962004419"
  },
  {
    "stck_bsop_date": "20260721",
    "stck_cntg_hour": "111000",
    "stck_prpr": "36045",
    "stck_oprc": "36125",
    "stck_hgpr": "36150",
    "stck_lwpr": "36020",
    "cntg_vol": "48068",
    "acml_tr_pbmn": "268697630512"
  },
  {
    "stck_bsop_date": "20260721",
    "stck_cntg_hour": "111100",
    "stck_prpr": "36115",
    "stck_oprc": "36045",
    "stck_hgpr": "36135",
    "stck_lwpr": "36000",
    "cntg_vol": "43652",
    "acml_tr_pbmn": "270271935817"
  },
  {
    "stck_bsop_date": "20260721",
    "stck_cntg_hour": "111200",
    "stck_prpr": "36085",
    "stck_oprc": "36130",
    "stck_hgpr": "36130",
    "stck_lwpr": "36050",
    "cntg_vol": "27586",
    "acml_tr_pbmn": "271267323907"
  },
  {
    "stck_bsop_date": "20260721",
    "stck_cntg_hour": "111300",
    "stck_prpr": "36150",
    "stck_oprc": "36075",
    "stck_hgpr": "36195",
    "stck_lwpr": "36075",
    "cntg_vol": "44174",
    "acml_tr_pbmn": "272864169207"
  },
  {
    "stck_bsop_date": "20260721",
    "stck_cntg_hour": "111400",
    "stck_prpr": "36200",
    "stck_oprc": "36140",
    "stck_hgpr": "36210",
    "stck_lwpr": "36135",
    "cntg_vol": "17048",
    "acml_tr_pbmn": "273481024729"
  },
  {
    "stck_bsop_date": "20260721",
    "stck_cntg_hour": "111500",
    "stck_prpr": "36170",
    "stck_oprc": "36200",
    "stck_hgpr": "36205",
    "stck_lwpr": "36165",
    "cntg_vol": "14760",
    "acml_tr_pbmn": "274015092154"
  }
]