[
  {
    "stck_bsop_date": "20260723",
    "stck_cntg_hour": "090000",
    "stck_prpr": "64500",
    "stck_oprc": "64500",
    "stck_hgpr": "65100",
    "stck_lwpr": "63500",
    "cntg_vol": "289807",
    "acml_tr_pbmn": "18705516750"
  },
  {
    "stck_bsop_date": "20260723",
    "stck_cntg_hour": "090100",
    "stck_prpr": "65300",
    "stck_oprc": "64600",
    "stck_hgpr": "66400",
    "stck_lwpr": "64500",
    "cntg_vol": "305992",
    "acml_tr_pbmn": "38854652900"
  },
  {
    "stck_bsop_date": "20260723",
    "stck_cntg_hour": "090200",
    "stck_prpr": "65800",
    "stck_oprc": "65300",
    "stck_hgpr": "66400",
    "stck_lwpr": "64200",
    "cntg_vol": "183902",
    "acml_tr_pbmn": "50875587250"
  },
  {
    "stck_bsop_date": "20260723",
    "stck_cntg_hour": "090300",
    "stck_prpr": "67500",
    "stck_oprc": "65700",
    "stck_hgpr": "67700",
    "stck_lwpr": "65300",
    "cntg_vol": "341721",
    "acml_tr_pbmn": "73770055150"
  },
  {
    "stck_bsop_date": "20260723",
    "stck_cntg_hour": "090400",
    "stck_prpr": "68800",
    "stck_oprc": "67400",
    "stck_hgpr": "69100",
    "stck_lwpr": "67100",
    "cntg_vol": "386606",
    "acml_tr_pbmn": "100190819000"
  },
  {
    "stck_bsop_date": "20260723",
    "stck_cntg_hour": "090500",
    "stck_prpr": "68800",
    "stck_oprc": "68800",
    "stck_hgpr": "69300",
    "stck_lwpr": "68300",
    "cntg_vol": "245818",
    "acml_tr_pbmn": "117113906900"
  },
  {
    "stck_bsop_date": "20260723",
    "stck_cntg_hour": "090600",
    "stck_prpr": "70700",
    "stck_oprc": "68800",
    "stck_hgpr": "70900",
    "stck_lwpr": "68700",
    "cntg_vol": "443919",
    "acml_tr_pbmn": "148272787550"
  },
  {
    "stck_bsop_date": "20260723",
    "stck_cntg_hour": "090700",
    "stck_prpr": "70700",
    "stck_oprc": "70700",
    "stck_hgpr": "70700",
    "stck_lwpr": "70700",
    "cntg_vol": "0",
    "acml_tr_pbmn": "148272787550"
  },
  {
    "stck_bsop_date": "20260723",
    "stck_cntg_hour": "090800",
    "stck_prpr": "70700",
    "stck_oprc": "70700",
    "stck_hgpr": "70700",
    "stck_lwpr": "70700",
    "cntg_vol": "0",
    "acml_tr_pbmn": "148272787550"
  },
  {
    "stck_bsop_date": "20260723",
    "stck_cntg_hour": "090900",
    "stck_prpr": "70900",
    "stck_oprc": "70800",
    "stck_hgpr": "70900",
    "stck_lwpr": "69900",
    "cntg_vol": "180333",
    "acml_tr_pbmn": "160971602700"
  }
]