[
  {
    "time": "09:08:43",
    "candidates": [
      {
        "code": "066430",
        "name": "066430",
        "price": 2425.0,
        "open": 2040.0,
        "gap_from_open_pct": 18.87,
        "approx_execution_strength": null,
        "market_cap": 949.0
      }
    ]
  },
  {
    "time": "09:16:32",
    "candidates": [
      {
        "code": "138360",
        "name": "138360",
        "price": 2340.0,
        "open": 1994.0,
        "gap_from_open_pct": 17.35,
        "approx_execution_strength": 77.7,
        "market_cap": 2118.0
      },
      {
        "code": "090710",
        "name": "090710",
        "price": 7550.0,
        "open": 7070.0,
        "gap_from_open_pct": 6.79,
        "approx_execution_strength": 393.7,
        "market_cap": 9027.0
      },
      {
        "code": "066430",
        "name": "066430",
        "price": 2425.0,
        "open": 2040.0,
        "gap_from_open_pct": 18.87,
        "approx_execution_strength": null,
        "market_cap": 949.0
      }
    ]
  },
  {
    "time": "09:25:10",
    "candidates": [
      {
        "code": "138360",
        "name": "138360",
        "price": 2330.0,
        "open": 1994.0,
        "gap_from_open_pct": 16.85,
        "approx_execution_strength": 357.8,
        "market_cap": 2109.0
      },
      {
        "code": "090710",
        "name": "090710",
        "price": 7260.0,
        "open": 7070.0,
        "gap_from_open_pct": 2.69,
        "approx_execution_strength": 50.2,
        "market_cap": 8680.0
      },
      {
        "code": "010170",
        "name": "010170",
        "price": 10870.0,
        "open": 10470.0,
        "gap_from_open_pct": 3.82,
        "approx_execution_strength": 224.6,
        "market_cap": 16901.0
      },
      {
        "code": "0148J0",
        "name": "0148J0",
        "price": 8800.0,
        "open": 8665.0,
        "gap_from_open_pct": 1.56,
        "approx_execution_strength": 4098.2,
        "market_cap": 5456.0
      }
    ]
  },
  {
    "time": "09:34:30",
    "candidates": [
      {
        "code": "138360",
        "name": "138360",
        "price": 2310.0,
        "open": 1994.0,
        "gap_from_open_pct": 15.85,
        "approx_execution_strength": 358.4,
        "market_cap": 2091.0
      },
      {
        "code": "010170",
        "name": "010170",
        "price": 10810.0,
        "open": 10470.0,
        "gap_from_open_pct": 3.25,
        "approx_execution_strength": 2960.0,
        "market_cap": 16808.0
      }
    ]
  },
  {
    "time": "09:44:08",
    "candidates": [
      {
        "code": "138360",
        "name": "138360",
        "price": 2285.0,
        "open": 1994.0,
        "gap_from_open_pct": 14.59,
        "approx_execution_strength": 168.0,
        "market_cap": 2068.0
      },
      {
        "code": "010170",
        "name": "010170",
        "price": 10660.0,
        "open": 10470.0,
        "gap_from_open_pct": 1.81,
        "approx_execution_strength": 62.1,
        "market_cap": 16575.0
      }
    ]
  },
  {
    "time": "09:53:53",
    "candidates": [
      {
        "code": "138360",
        "name": "138360",
        "price": 2275.0,
        "open": 1994.0,
        "gap_from_open_pct": 14.09,
        "approx_execution_strength": 110.6,
        "market_cap": 2059.0
      },
      {
        "code": "010170",
        "name": "010170",
        "price": 10650.0,
        "open": 10470.0,
        "gap_from_open_pct": 1.72,
        "approx_execution_strength": 1344.9,
        "market_cap": 16559.0
      }
    ]
  },
  {
    "time": "10:03:49",
    "candidates": [
      {
        "code": "138360",
        "name": "138360",
        "price": 2325.0,
        "open": 1994.0,
        "gap_from_open_pct": 16.6,
        "approx_execution_strength": 6486.8,
        "market_cap": 2104.0
      }
    ]
  },
  {
    "time": "10:13:43",
    "candidates": [
      {
        "code": "138360",
        "name": "138360",
        "price": 2325.0,
        "open": 1994.0,
        "gap_from_open_pct": 16.6,
        "approx_execution_strength": 79.3,
        "market_cap": 2104.0
      },
      {
        "code": "0148J0",
        "name": "0148J0",
        "price": 9145.0,
        "open": 8665.0,
        "gap_from_open_pct": 5.54,
        "approx_execution_strength": 3144.8,
        "market_cap": 5670.0
      },
      {
        "code": "090710",
        "name": "090710",
        "price": 7660.0,
        "open": 7070.0,
        "gap_from_open_pct": 8.35,
        "approx_execution_strength": 50.5,
        "market_cap": 9158.0
      }
    ]
  },
  {
    "time": "10:23:29",
    "candidates": [
      {
        "code": "138360",
        "name": "138360",
        "price": 2365.0,
        "open": 1994.0,
        "gap_from_open_pct": 18.61,
        "approx_execution_strength": 991.4,
        "market_cap": 2140.0
      },
      {
        "code": "090710",
        "name": "090710",
        "price": 7560.0,
        "open": 7070.0,
        "gap_from_open_pct": 6.93,
        "approx_execution_strength": 4461.3,
        "market_cap": 9039.0
      },
      {
        "code": "0148J0",
        "name": "0148J0",
        "price": 9130.0,
        "open": 8665.0,
        "gap_from_open_pct": 5.37,
        "approx_execution_strength": 2544.6,
        "market_cap": 5661.0
      }
    ]
  },
  {
    "time": "10:32:58",
    "candidates": [
      {
        "code": "138360",
        "name": "138360",
        "price": 2360.0,
        "open": 1994.0,
        "gap_from_open_pct": 18.36,
        "approx_execution_strength": 1031.3,
        "market_cap": 2136.0
      },
      {
        "code": "090710",
        "name": "090710",
        "price": 7290.0,
        "open": 7070.0,
        "gap_from_open_pct": 3.11,
        "approx_execution_strength": 1637.8,
        "market_cap": 8716.0
      },
      {
        "code": "0148J0",
        "name": "0148J0",
        "price": 8865.0,
        "open": 8665.0,
        "gap_from_open_pct": 2.31,
        "approx_execution_strength": 966.7,
        "market_cap": 5496.0
      }
    ]
  },
  {
    "time": "10:42:13",
    "candidates": [
      {
        "code": "138360",
        "name": "138360",
        "price": 2370.0,
        "open": 1994.0,
        "gap_from_open_pct": 18.86,
        "approx_execution_strength": 1426.0,
        "market_cap": 2145.0
      },
      {
        "code": "090710",
        "name": "090710",
        "price": 7210.0,
        "open": 7070.0,
        "gap_from_open_pct": 1.98,
        "approx_execution_strength": 101.2,
        "market_cap": 8620.0
      },
      {
        "code": "0148J0",
        "name": "0148J0",
        "price": 8835.0,
        "open": 8665.0,
        "gap_from_open_pct": 1.96,
        "approx_execution_strength": 245.7,
        "market_cap": 5478.0
      }
    ]
  },
  {
    "time": "10:51:57",
    "candidates": [
      {
        "code": "138360",
        "name": "138360",
        "price": 2355.0,
        "open": 1994.0,
        "gap_from_open_pct": 18.1,
        "approx_execution_strength": 74.9,
        "market_cap": 2131.0
      },
      {
        "code": "069500",
        "name": "069500",
        "price": 114700.0,
        "open": 113570.0,
        "gap_from_open_pct": 0.99,
        "approx_execution_strength": 225.7,
        "market_cap": 258247.0
      },
      {
        "code": "090710",
        "name": "090710",
        "price": 7350.0,
        "open": 7070.0,
        "gap_from_open_pct": 3.96,
        "approx_execution_strength": 1371.5,
        "market_cap": 8788.0
      },
      {
        "code": "0148J0",
        "name": "0148J0",
        "price": 8965.0,
        "open": 8665.0,
        "gap_from_open_pct": 3.46,
        "approx_execution_strength": 821.1,
        "market_cap": 5558.0
      }
    ]
  },
  {
    "time": "11:01:34",
    "candidates": [
      {
        "code": "138360",
        "name": "138360",
        "price": 2360.0,
        "open": 1994.0,
        "gap_from_open_pct": 18.36,
        "approx_execution_strength": 66.7,
        "market_cap": 2136.0
      },
      {
        "code": "069500",
        "name": "069500",
        "price": 114250.0,
        "open": 113570.0,
        "gap_from_open_pct": 0.6,
        "approx_execution_strength": 33.4,
        "market_cap": 257234.0
      },
      {
        "code": "090710",
        "name": "090710",
        "price": 7380.0,
        "open": 7070.0,
        "gap_from_open_pct": 4.38,
        "approx_execution_strength": 704.1,
        "market_cap": 8823.0
      },
      {
        "code": "0148J0",
        "name": "0148J0",
        "price": 8935.0,
        "open": 8665.0,
        "gap_from_open_pct": 3.12,
        "approx_execution_strength": 442.7,
        "market_cap": 5540.0
      }
    ]
  },
  {
    "time": "11:11:27",
    "candidates": [
      {
        "code": "138360",
        "name": "138360",
        "price": 2362.0,
        "open": 1994.0,
        "gap_from_open_pct": 18.46,
        "approx_execution_strength": 2505.5,
        "market_cap": 2138.0
      },
      {
        "code": "069500",
        "name": "069500",
        "price": 114150.0,
        "open": 113570.0,
        "gap_from_open_pct": 0.51,
        "approx_execution_strength": 1081.2,
        "market_cap": 257009.0
      },
      {
        "code": "090710",
        "name": "090710",
        "price": 7380.0,
        "open": 7070.0,
        "gap_from_open_pct": 4.38,
        "approx_execution_strength": 1359.4,
        "market_cap": 8823.0
      },
      {
        "code": "0148J0",
        "name": "0148J0",
        "price": 8980.0,
        "open": 8665.0,
        "gap_from_open_pct": 3.64,
        "approx_execution_strength": 463.8,
        "market_cap": 5568.0
      }
    ]
  },
  {
    "time": "11:20:27",
    "candidates": [
      {
        "code": "138360",
        "name": "138360",
        "price": 2390.0,
        "open": 1994.0,
        "gap_from_open_pct": 19.86,
        "approx_execution_strength": null,
        "market_cap": 2163.0
      },
      {
        "code": "069500",
        "name": "069500",
        "price": 114255.0,
        "open": 113570.0,
        "gap_from_open_pct": 0.6,
        "approx_execution_strength": 223.4,
        "market_cap": 257245.0
      },
      {
        "code": "090710",
        "name": "090710",
        "price": 7400.0,
        "open": 7070.0,
        "gap_from_open_pct": 4.67,
        "approx_execution_strength": 280.2,
        "market_cap": 8847.0
      },
      {
        "code": "0148J0",
        "name": "0148J0",
        "price": 8975.0,
        "open": 8665.0,
        "gap_from_open_pct": 3.58,
        "approx_execution_strength": 55687.5,
        "market_cap": 5565.0
      }
    ]
  },
  {
    "time": "11:29:38",
    "candidates": [
      {
        "code": "138360",
        "name": "138360",
        "price": 2390.0,
        "open": 1994.0,
        "gap_from_open_pct": 19.86,
        "approx_execution_strength": null,
        "market_cap": 2163.0
      },
      {
        "code": "069500",
        "name": "069500",
        "price": 114400.0,
        "open": 113570.0,
        "gap_from_open_pct": 0.73,
        "approx_execution_strength": 78.0,
        "market_cap": 257572.0
      },
      {
        "code": "090710",
        "name": "090710",
        "price": 7460.0,
        "open": 7070.0,
        "gap_from_open_pct": 5.52,
        "approx_execution_strength": 146.4,
        "market_cap": 8919.0
      },
      {
        "code": "0148J0",
        "name": "0148J0",
        "price": 8950.0,
        "open": 8665.0,
        "gap_from_open_pct": 3.29,
        "approx_execution_strength": 61.7,
        "market_cap": 5549.0
      }
    ]
  },
  {
    "time": "11:38:55",
    "candidates": [
      {
        "code": "138360",
        "name": "138360",
        "price": 2390.0,
        "open": 1994.0,
        "gap_from_open_pct": 19.86,
        "approx_execution_strength": null,
        "market_cap": 2163.0
      },
      {
        "code": "090710",
        "name": "090710",
        "price": 7330.0,
        "open": 7070.0,
        "gap_from_open_pct": 3.68,
        "approx_execution_strength": 86.0,
        "market_cap": 8764.0
      }
    ]
  },
  {
    "time": "11:48:23",
    "candidates": [
      {
        "code": "138360",
        "name": "138360",
        "price": 2390.0,
        "open": 1994.0,
        "gap_from_open_pct": 19.86,
        "approx_execution_strength": null,
        "market_cap": 2163.0
      },
      {
        "code": "090710",
        "name": "090710",
        "price": 7300.0,
        "open": 7070.0,
        "gap_from_open_pct": 3.25,
        "approx_execution_strength": 51.3,
        "market_cap": 8728.0
      }
    ]
  },
  {
    "time": "11:57:55",
    "candidates": [
      {
        "code": "138360",
        "name": "138360",
        "price": 2390.0,
        "open": 1994.0,
        "gap_from_open_pct": 19.86,
        "approx_execution_strength": null,
        "market_cap": 2163.0
      },
      {
        "code": "090710",
        "name": "090710",
        "price": 7290.0,
        "open": 7070.0,
        "gap_from_open_pct": 3.11,
        "approx_execution_strength": 227.3,
        "market_cap": 8716.0
      }
    ]
  },
  {
    "time": "12:07:34",
    "candidates": [
      {
        "code": "138360",
        "name": "138360",
        "price": 2390.0,
        "open": 1994.0,
        "gap_from_open_pct": 19.86,
        "approx_execution_strength": null,
        "market_cap": 2163.0
      },
      {
        "code": "090710",
        "name": "090710",
        "price": 7250.0,
        "open": 7070.0,
        "gap_from_open_pct": 2.55,
        "approx_execution_strength": 1494.3,
        "market_cap": 8668.0
      }
    ]
  },
  {
    "time": "12:16:05",
    "candidates": [
      {
        "code": "138360",
        "name": "138360",
        "price": 2390.0,
        "open": 1994.0,
        "gap_from_open_pct": 19.86,
        "approx_execution_strength": null,
        "market_cap": 2163.0
      }
    ]
  },
  {
    "time": "12:25:44",
    "candidates": [
      {
        "code": "138360",
        "name": "138360",
        "price": 2390.0,
        "open": 1994.0,
        "gap_from_open_pct": 19.86,
        "approx_execution_strength": null,
        "market_cap": 2163.0
      }
    ]
  },
  {
    "time": "12:34:29",
    "candidates": [
      {
        "code": "138360",
        "name": "138360",
        "price": 2390.0,
        "open": 1994.0,
        "gap_from_open_pct": 19.86,
        "approx_execution_strength": null,
        "market_cap": 2163.0
      }
    ]
  }
]