[
  {
    "bsop_hour": "090647",
    "stck_prpr": "236500",
    "prdy_vrss": "12500",
    "prdy_vrss_sign": "2",
    "prdy_ctrt": "5.58",
    "acml_vol": "115791",
    "whol_smtn_seln_vol": "59836",
    "whol_smtn_shnu_vol": "38817",
    "whol_smtn_ntby_qty": "-21019",
    "whol_smtn_seln_tr_pbmn": "14163992250",
    "whol_smtn_shnu_tr_pbmn": "9207312250",
    "whol_smtn_ntby_tr_pbmn": "-4956680000",
    "whol_ntby_vol_icdc": "-10",
    "whol_ntby_tr_pbmn_icdc": "-2365000"
  },
  {
    "bsop_hour": "090652",
    "stck_prpr": "236500",
    "prdy_vrss": "12500",
    "prdy_vrss_sign": "2",
    "prdy_ctrt": "5.58",
    "acml_vol": "116123",
    "whol_smtn_seln_vol": "59901",
    "whol_smtn_shnu_vol": "38817",
    "whol_smtn_ntby_qty": "-21084",
    "whol_smtn_seln_tr_pbmn": "14179365750",
    "whol_smtn_shnu_tr_pbmn": "9207312250",
    "whol_smtn_ntby_tr_pbmn": "-4972053500",
    "whol_ntby_vol_icdc": "-65",
    "whol_ntby_tr_pbmn_icdc": "-15373500"
  },
  {
    "bsop_hour": "090657",
    "stck_prpr": "236500",
    "prdy_vrss": "12500",
    "prdy_vrss_sign": "2",
    "prdy_ctrt": "5.58",
    "acml_vol": "116637",
    "whol_smtn_seln_vol": "60018",
    "whol_smtn_shnu_vol": "38817",
    "whol_smtn_ntby_qty": "-21201",
    "whol_smtn_seln_tr_pbmn": "14207094750",
    "whol_smtn_shnu_tr_pbmn": "9207312250",
    "whol_smtn_ntby_tr_pbmn": "-4999782500",
    "whol_ntby_vol_icdc": "-117",
    "whol_ntby_tr_pbmn_icdc": "-27729000"
  },
  {
    "bsop_hour": "090702",
    "stck_prpr": "236500",
    "prdy_vrss": "12500",
    "prdy_vrss_sign": "2",
    "prdy_ctrt": "5.58",
    "acml_vol": "116873",
    "whol_smtn_seln_vol": "60018",
    "whol_smtn_shnu_vol": "38817",
    "whol_smtn_ntby_qty": "-21201",
    "whol_smtn_seln_tr_pbmn": "14207094750",
    "whol_smtn_shnu_tr_pbmn": "9207312250",
    "whol_smtn_ntby_tr_pbmn": "-4999782500",
    "whol_ntby_vol_icdc": "0",
    "whol_ntby_tr_pbmn_icdc": "0"
  },
  {
    "bsop_hour": "090706",
    "stck_prpr": "237000",
    "prdy_vrss": "13000",
    "prdy_vrss_sign": "2",
    "prdy_ctrt": "5.80",
    "acml_vol": "117029",
    "whol_smtn_seln_vol": "60039",
    "whol_smtn_shnu_vol": "38817",
    "whol_smtn_ntby_qty": "-21222",
    "whol_smtn_seln_tr_pbmn": "14212061250",
    "whol_smtn_shnu_tr_pbmn": "9207312250",
    "whol_smtn_ntby_tr_pbmn": "-5004749000",
    "whol_ntby_vol_icdc": "-21",
    "whol_ntby_tr_pbmn_icdc": "-4966500"
  },
  {
    "bsop_hour": "090717",
    "stck_prpr": "237000",
    "prdy_vrss": "13000",
    "prdy_vrss_sign": "2",
    "prdy_ctrt": "5.80",
    "acml_vol": "117597",
    "whol_smtn_seln_vol": "60129",
    "whol_smtn_shnu_vol": "38817",
    "whol_smtn_ntby_qty": "-21312",
    "whol_smtn_seln_tr_pbmn": "14233392250",
    "whol_smtn_shnu_tr_pbmn": "9207312250",
    "whol_smtn_ntby_tr_pbmn": "-5026080000",
    "whol_ntby_vol_icdc": "-90",
    "whol_ntby_tr_pbmn_icdc": "-21331000"
  },
  {
    "bsop_hour": "090727",
    "stck_prpr": "237000",
    "prdy_vrss": "13000",
    "prdy_vrss_sign": "2",
    "prdy_ctrt": "5.80",
    "acml_vol": "117775",
    "whol_smtn_seln_vol": "60145",
    "whol_smtn_shnu_vol": "38817",
    "whol_smtn_ntby_qty": "-21328",
    "whol_smtn_seln_tr_pbmn": "14237192250",
    "whol_smtn_shnu_tr_pbmn": "9207312250",
    "whol_smtn_ntby_tr_pbmn": "-5029880000",
    "whol_ntby_vol_icdc": "-16",
    "whol_ntby_tr_pbmn_icdc": "-3800000"
  },
  {
    "bsop_hour": "090739",
    "stck_prpr": "237500",
    "prdy_vrss": "13500",
    "prdy_vrss_sign": "2",
    "prdy_ctrt": "6.03",
    "acml_vol": "118063",
    "whol_smtn_seln_vol": "60252",
    "whol_smtn_shnu_vol": "38817",
    "whol_smtn_ntby_qty": "-21435",
    "whol_smtn_seln_tr_pbmn": "14262604750",
    "whol_smtn_shnu_tr_pbmn": "9207312250",
    "whol_smtn_ntby_tr_pbmn": "-5055292500",
    "whol_ntby_vol_icdc": "-107",
    "whol_ntby_tr_pbmn_icdc": "-25412500"
  },
  {
    "bsop_hour": "090742",
    "stck_prpr": "237500",
    "prdy_vrss": "13500",
    "prdy_vrss_sign": "2",
    "prdy_ctrt": "6.03",
    "acml_vol": "118257",
    "whol_smtn_seln_vol": "60273",
    "whol_smtn_shnu_vol": "38817",
    "whol_smtn_ntby_qty": "-21456",
    "whol_smtn_seln_tr_pbmn": "14267592250",
    "whol_smtn_shnu_tr_pbmn": "9207312250",
    "whol_smtn_ntby_tr_pbmn": "-5060280000",
    "whol_ntby_vol_icdc": "-21",
    "whol_ntby_tr_pbmn_icdc": "-4987500"
  },
  {
    "bsop_hour": "090750",
    "stck_prpr": "237500",
    "prdy_vrss": "13500",
    "prdy_vrss_sign": "2",
    "prdy_ctrt": "6.03",
    "acml_vol": "118475",
    "whol_smtn_seln_vol": "60273",
    "whol_smtn_shnu_vol": "38817",
    "whol_smtn_ntby_qty": "-21456",
    "whol_smtn_seln_tr_pbmn": "14267592250",
    "whol_smtn_shnu_tr_pbmn": "9207312250",
    "whol_smtn_ntby_tr_pbmn": "-5060280000",
    "whol_ntby_vol_icdc": "0",
    "whol_ntby_tr_pbmn_icdc": "0"
  },
  {
    "bsop_hour": "090810",
    "stck_prpr": "238000",
    "prdy_vrss": "14000",
    "prdy_vrss_sign": "2",
    "prdy_ctrt": "6.25",
    "acml_vol": "119010",
    "whol_smtn_seln_vol": "60341",
    "whol_smtn_shnu_vol": "38817",
    "whol_smtn_ntby_qty": "-21524",
    "whol_smtn_seln_tr_pbmn": "14283776250",
    "whol_smtn_shnu_tr_pbmn": "9207312250",
    "whol_smtn_ntby_tr_pbmn": "-5076464000",
    "whol_ntby_vol_icdc": "-68",
    "whol_ntby_tr_pbmn_icdc": "-16184000"
  },
  {
    "bsop_hour": "090813",
    "stck_prpr": "238000",
    "prdy_vrss": "14000",
    "prdy_vrss_sign": "2",
    "prdy_ctrt": "6.25",
    "acml_vol": "119579",
    "whol_smtn_seln_vol": "60910",
    "whol_smtn_shnu_vol": "38817",
    "whol_smtn_ntby_qty": "-22093",
    "whol_smtn_seln_tr_pbmn": "14418915750",
    "whol_smtn_shnu_tr_pbmn": "9207312250",
    "whol_smtn_ntby_tr_pbmn": "-5211603500",
    "whol_ntby_vol_icdc": "-569",
    "whol_ntby_tr_pbmn_icdc": "-135139500"
  },
  {
    "bsop_hour": "090817",
    "stck_prpr": "238000",
    "prdy_vrss": "14000",
    "prdy_vrss_sign": "2",
    "prdy_ctrt": "6.25",
    "acml_vol": "119580",
    "whol_smtn_seln_vol": "60911",
    "whol_smtn_shnu_vol": "38817",
    "whol_smtn_ntby_qty": "-22094",
    "whol_smtn_seln_tr_pbmn": "14419153750",
    "whol_smtn_shnu_tr_pbmn": "9207312250",
    "whol_smtn_ntby_tr_pbmn": "-5211841500",
    "whol_ntby_vol_icdc": "-1",
    "whol_ntby_tr_pbmn_icdc": "-238000"
  },
  {
    "bsop_hour": "090820",
    "stck_prpr": "237500",
    "prdy_vrss": "13500",
    "prdy_vrss_sign": "2",
    "prdy_ctrt": "6.03",
    "acml_vol": "119638",
    "whol_smtn_seln_vol": "60956",
    "whol_smtn_shnu_vol": "38817",
    "whol_smtn_ntby_qty": "-22139",
    "whol_smtn_seln_tr_pbmn": "14429863750",
    "whol_smtn_shnu_tr_pbmn": "9207312250",
    "whol_smtn_ntby_tr_pbmn": "-5222551500",
    "whol_ntby_vol_icdc": "-45",
    "whol_ntby_tr_pbmn_icdc": "-10710000"
  },
  {
    "bsop_hour": "090825",
    "stck_prpr": "238000",
    "prdy_vrss": "14000",
    "prdy_vrss_sign": "2",
    "prdy_ctrt": "6.25",
    "acml_vol": "120126",
    "whol_smtn_seln_vol": "61050",
    "whol_smtn_shnu_vol": "38817",
    "whol_smtn_ntby_qty": "-22233",
    "whol_smtn_seln_tr_pbmn": "14452235750",
    "whol_smtn_shnu_tr_pbmn": "9207312250",
    "whol_smtn_ntby_tr_pbmn": "-5244923500",
    "whol_ntby_vol_icdc": "-94",
    "whol_ntby_tr_pbmn_icdc": "-22372000"
  },
  {
    "bsop_hour": "090828",
    "stck_prpr": "238000",
    "prdy_vrss": "14000",
    "prdy_vrss_sign": "2",
    "prdy_ctrt": "6.25",
    "acml_vol": "120389",
    "whol_smtn_seln_vol": "61117",
    "whol_smtn_shnu_vol": "38817",
    "whol_smtn_ntby_qty": "-22300",
    "whol_smtn_seln_tr_pbmn": "14468181750",
    "whol_smtn_shnu_tr_pbmn": "9207312250",
    "whol_smtn_ntby_tr_pbmn": "-5260869500",
    "whol_ntby_vol_icdc": "-67",
    "whol_ntby_tr_pbmn_icdc": "-15946000"
  },
  {
    "bsop_hour": "090830",
    "stck_prpr": "238000",
    "prdy_vrss": "14000",
    "prdy_vrss_sign": "2",
    "prdy_ctrt": "6.25",
    "acml_vol": "120435",
    "whol_smtn_seln_vol": "61152",
    "whol_smtn_shnu_vol": "38817",
    "whol_smtn_ntby_qty": "-22335",
    "whol_smtn_seln_tr_pbmn": "14476511750",
    "whol_smtn_shnu_tr_pbmn": "9207312250",
    "whol_smtn_ntby_tr_pbmn": "-5269199500",
    "whol_ntby_vol_icdc": "-35",
    "whol_ntby_tr_pbmn_icdc": "-8330000"
  },
  {
    "bsop_hour": "090837",
    "stck_prpr": "238000",
    "prdy_vrss": "14000",
    "prdy_vrss_sign": "2",
    "prdy_ctrt": "6.25",
    "acml_vol": "121111",
    "whol_smtn_seln_vol": "61182",
    "whol_smtn_shnu_vol": "38817",
    "whol_smtn_ntby_qty": "-22365",
    "whol_smtn_seln_tr_pbmn": "14483651750",
    "whol_smtn_shnu_tr_pbmn": "9207312250",
    "whol_smtn_ntby_tr_pbmn": "-5276339500",
    "whol_ntby_vol_icdc": "-30",
    "whol_ntby_tr_pbmn_icdc": "-7140000"
  },
  {
    "bsop_hour": "090839",
    "stck_prpr": "237500",
    "prdy_vrss": "13500",
    "prdy_vrss_sign": "2",
    "prdy_ctrt": "6.03",
    "acml_vol": "121112",
    "whol_smtn_seln_vol": "61182",
    "whol_smtn_shnu_vol": "38817",
    "whol_smtn_ntby_qty": "-22365",
    "whol_smtn_seln_tr_pbmn": "14483651750",
    "whol_smtn_shnu_tr_pbmn": "9207312250",
    "whol_smtn_ntby_tr_pbmn": "-5276339500",
    "whol_ntby_vol_icdc": "0",
    "whol_ntby_tr_pbmn_icdc": "0"
  },
  {
    "bsop_hour": "090842",
    "stck_prpr": "238000",
    "prdy_vrss": "14000",
    "prdy_vrss_sign": "2",
    "prdy_ctrt": "6.25",
    "acml_vol": "121277",
    "whol_smtn_seln_vol": "61258",
    "whol_smtn_shnu_vol": "38817",
    "whol_smtn_ntby_qty": "-22441",
    "whol_smtn_seln_tr_pbmn": "14501739750",
    "whol_smtn_shnu_tr_pbmn": "9207312250",
    "whol_smtn_ntby_tr_pbmn": "-5294427500",
    "whol_ntby_vol_icdc": "-76",
    "whol_ntby_tr_pbmn_icdc": "-18088000"
  },
  {
    "bsop_hour": "090846",
    "stck_prpr": "238000",
    "prdy_vrss": "14000",
    "prdy_vrss_sign": "2",
    "prdy_ctrt": "6.25",
    "acml_vol": "121295",
    "whol_smtn_seln_vol": "61258",
    "whol_smtn_shnu_vol": "38817",
    "whol_smtn_ntby_qty": "-22441",
    "whol_smtn_seln_tr_pbmn": "14501739750",
    "whol_smtn_shnu_tr_pbmn": "9207312250",
    "whol_smtn_ntby_tr_pbmn": "-5294427500",
    "whol_ntby_vol_icdc": "0",
    "whol_ntby_tr_pbmn_icdc": "0"
  },
  {
    "bsop_hour": "090852",
    "stck_prpr": "238000",
    "prdy_vrss": "14000",
    "prdy_vrss_sign": "2",
    "prdy_ctrt": "6.25",
    "acml_vol": "121453",
    "whol_smtn_seln_vol": "61270",
    "whol_smtn_shnu_vol": "38817",
    "whol_smtn_ntby_qty": "-22453",
    "whol_smtn_seln_tr_pbmn": "14504595750",
    "whol_smtn_shnu_tr_pbmn": "9207312250",
    "whol_smtn_ntby_tr_pbmn": "-5297283500",
    "whol_ntby_vol_icdc": "-12",
    "whol_ntby_tr_pbmn_icdc": "-2856000"
  },
  {
    "bsop_hour": "090858",
    "stck_prpr": "237500",
    "prdy_vrss": "13500",
    "prdy_vrss_sign": "2",
    "prdy_ctrt": "6.03",
    "acml_vol": "122284",
    "whol_smtn_seln_vol": "61909",
    "whol_smtn_shnu_vol": "38817",
    "whol_smtn_ntby_qty": "-23092",
    "whol_smtn_seln_tr_pbmn": "14656358750",
    "whol_smtn_shnu_tr_pbmn": "9207312250",
    "whol_smtn_ntby_tr_pbmn": "-5449046500",
    "whol_ntby_vol_icdc": "-639",
    "whol_ntby_tr_pbmn_icdc": "-151763000"
  },
  {
    "bsop_hour": "090901",
    "stck_prpr": "237500",
    "prdy_vrss": "13500",
    "prdy_vrss_sign": "2",
    "prdy_ctrt": "6.03",
    "acml_vol": "122323",
    "whol_smtn_seln_vol": "61909",
    "whol_smtn_shnu_vol": "38817",
    "whol_smtn_ntby_qty": "-23092",
    "whol_smtn_seln_tr_pbmn": "14656358750",
    "whol_smtn_shnu_tr_pbmn": "9207312250",
    "whol_smtn_ntby_tr_pbmn": "-5449046500",
    "whol_ntby_vol_icdc": "0",
    "whol_ntby_tr_pbmn_icdc": "0"
  },
  {
    "bsop_hour": "090905",
    "stck_prpr": "237500",
    "prdy_vrss": "13500",
    "prdy_vrss_sign": "2",
    "prdy_ctrt": "6.03",
    "acml_vol": "122467",
    "whol_smtn_seln_vol": "61942",
    "whol_smtn_shnu_vol": "38817",
    "whol_smtn_ntby_qty": "-23125",
    "whol_smtn_seln_tr_pbmn": "14664196250",
    "whol_smtn_shnu_tr_pbmn": "9207312250",
    "whol_smtn_ntby_tr_pbmn": "-5456884000",
    "whol_ntby_vol_icdc": "-33",
    "whol_ntby_tr_pbmn_icdc": "-7837500"
  },
  {
    "bsop_hour": "090908",
    "stck_prpr": "237500",
    "prdy_vrss": "13500",
    "prdy_vrss_sign": "2",
    "prdy_ctrt": "6.03",
    "acml_vol": "122572",
    "whol_smtn_seln_vol": "61953",
    "whol_smtn_shnu_vol": "38817",
    "whol_smtn_ntby_qty": "-23136",
    "whol_smtn_seln_tr_pbmn": "14666808750",
    "whol_smtn_shnu_tr_pbmn": "9207312250",
    "whol_smtn_ntby_tr_pbmn": "-5459496500",
    "whol_ntby_vol_icdc": "-11",
    "whol_ntby_tr_pbmn_icdc": "-2612500"
  },
  {
    "bsop_hour": "090911",
    "stck_prpr": "237500",
    "prdy_vrss": "13500",
    "prdy_vrss_sign": "2",
    "prdy_ctrt": "6.03",
    "acml_vol": "122583",
    "whol_smtn_seln_vol": "61953",
    "whol_smtn_shnu_vol": "38817",
    "whol_smtn_ntby_qty": "-23136",
    "whol_smtn_seln_tr_pbmn": "14666808750",
    "whol_smtn_shnu_tr_pbmn": "9207312250",
    "whol_smtn_ntby_tr_pbmn": "-5459496500",
    "whol_ntby_vol_icdc": "0",
    "whol_ntby_tr_pbmn_icdc": "0"
  },
  {
    "bsop_hour": "090923",
    "stck_prpr": "237500",
    "prdy_vrss": "13500",
    "prdy_vrss_sign": "2",
    "prdy_ctrt": "6.03",
    "acml_vol": "122644",
    "whol_smtn_seln_vol": "61953",
    "whol_smtn_shnu_vol": "38817",
    "whol_smtn_ntby_qty": "-23136",
    "whol_smtn_seln_tr_pbmn": "14666808750",
    "whol_smtn_shnu_tr_pbmn": "9207312250",
    "whol_smtn_ntby_tr_pbmn": "-5459496500",
    "whol_ntby_vol_icdc": "0",
    "whol_ntby_tr_pbmn_icdc": "0"
  },
  {
    "bsop_hour": "090930",
    "stck_prpr": "237000",
    "prdy_vrss": "13000",
    "prdy_vrss_sign": "2",
    "prdy_ctrt": "5.80",
    "acml_vol": "122689",
    "whol_smtn_seln_vol": "61953",
    "whol_smtn_shnu_vol": "38817",
    "whol_smtn_ntby_qty": "-23136",
    "whol_smtn_seln_tr_pbmn": "14666808750",
    "whol_smtn_shnu_tr_pbmn": "9207312250",
    "whol_smtn_ntby_tr_pbmn": "-5459496500",
    "whol_ntby_vol_icdc": "0",
    "whol_ntby_tr_pbmn_icdc": "0"
  },
  {
    "bsop_hour": "090934",
    "stck_prpr": "237500",
    "prdy_vrss": "13500",
    "prdy_vrss_sign": "2",
    "prdy_ctrt": "6.03",
    "acml_vol": "122716",
    "whol_smtn_seln_vol": "61953",
    "whol_smtn_shnu_vol": "38817",
    "whol_smtn_ntby_qty": "-23136",
    "whol_smtn_seln_tr_pbmn": "14666808750",
    "whol_smtn_shnu_tr_pbmn": "9207312250",
    "whol_smtn_ntby_tr_pbmn": "-5459496500",
    "whol_ntby_vol_icdc": "0",
    "whol_ntby_tr_pbmn_icdc": "0"
  }
]